r7_surcom_sdk/__init__.py
r7_surcom_sdk/main.py
r7_surcom_sdk/cmds/__init__.py
r7_surcom_sdk/cmds/config/__init__.py
r7_surcom_sdk/cmds/config/add_connection.py
r7_surcom_sdk/cmds/config/delete_connection.py
r7_surcom_sdk/cmds/config/enable_tab_completion.py
r7_surcom_sdk/cmds/config/init.py
r7_surcom_sdk/cmds/config/list_connections.py
r7_surcom_sdk/cmds/config/set_default.py
r7_surcom_sdk/cmds/config/test_connection.py
r7_surcom_sdk/cmds/connector/__init__.py
r7_surcom_sdk/cmds/connector/codegen.py
r7_surcom_sdk/cmds/connector/init.py
r7_surcom_sdk/cmds/connector/install.py
r7_surcom_sdk/cmds/connector/invoke.py
r7_surcom_sdk/cmds/connector/package.py
r7_surcom_sdk/cmds/connector/sign.py
r7_surcom_sdk/cmds/connector/validate.py
r7_surcom_sdk/cmds/data/__init__.py
r7_surcom_sdk/cmds/data/import_data.py
r7_surcom_sdk/cmds/dev/__init__.py
r7_surcom_sdk/cmds/dev/ext_lib_docs.py
r7_surcom_sdk/cmds/model/__init__.py
r7_surcom_sdk/cmds/model/download.py
r7_surcom_sdk/cmds/type/__init__.py
r7_surcom_sdk/cmds/type/generate.py
r7_surcom_sdk/cmds/type/install.py
r7_surcom_sdk/data/cmds/connector/connector.spec.yaml.jinja2
r7_surcom_sdk/data/cmds/connector/codegen/icon.svg.jinja2
r7_surcom_sdk/data/cmds/connector/codegen/docs/1.png
r7_surcom_sdk/data/cmds/connector/codegen/docs/INSTRUCTIONS.md.jinja2
r7_surcom_sdk/data/cmds/connector/codegen/functions/__init__.py.jinja2
r7_surcom_sdk/data/cmds/connector/codegen/functions/__main__.py.jinja2
r7_surcom_sdk/data/cmds/connector/codegen/functions/fn_import.py.jinja2
r7_surcom_sdk/data/cmds/connector/codegen/functions/fn_test.py.jinja2
r7_surcom_sdk/data/cmds/connector/codegen/functions/helpers.py.jinja2
r7_surcom_sdk/data/cmds/connector/codegen/functions/sc_settings.py.jinja2
r7_surcom_sdk/data/cmds/connector/codegen/functions/sc_types.py.jinja2
r7_surcom_sdk/data/cmds/connector/codegen/types/surcom_type.yaml.jinja2
r7_surcom_sdk/data/cmds/connector/codegen/types/surcom_type_generated.yaml.jinja2
r7_surcom_sdk-0.10.12.dist-info/licenses/LICENSE
r7_surcom_sdk-0.10.12.dist-info/METADATA
r7_surcom_sdk-0.10.12.dist-info/WHEEL
r7_surcom_sdk-0.10.12.dist-info/entry_points.txt
r7_surcom_sdk-0.10.12.dist-info/top_level.txt
r7_surcom_sdk-0.10.12.dist-info/RECORD
